setup.py
hansol.egg-info/PKG-INFO
hansol.egg-info/SOURCES.txt
hansol.egg-info/dependency_links.txt
hansol.egg-info/requires.txt
hansol.egg-info/top_level.txt
solweek/__init__.py
solweek/yearweekFunc.py