Metadata-Version: 1.0
Name: hansol
Version: 0.0.1
Summary: Fintech API
Home-page: https://github.com/sol-91/pyPackage
Author: solhan
Author-email: sky910829@naver.com
License: MIT
Keywords: calendar,yearweek
Platform: UNKNOWN
